[
  {
    "icon": "zhuxianjuqing",
    "Difficulty": 0,
    "type": 1,
    "title": "achievementTitle110001",
    "desc": "achievementDesc110001",
    "count": 1,
    "value": "610354_610364",
    "condition": "0",
    "feature": 2416,
    "id": 110001,
    "isVariant": false,
    "isModExtend": false
  },
  {
    "icon": "zhuxianjuqing",
    "Difficulty": 0,
    "type": 1,
    "title": "achievementTitle110002",
    "desc": "achievementDesc110002",
    "count": 1,
    "value": "70703",
    "condition": "0",
    "feature": 2417,
    "id": 110002,
    "isVariant": false,
    "isModExtend": false
  },
  {
    "icon": "zhuxianjuqing",
    "Difficulty": 0,
    "type": 1,
    "title": "achievementTitle110003",
    "desc": "achievementDesc110003",
    "count": 1,
    "value": "71473_71483_71493_71503",
    "condition": "0",
    "feature": 2418,
    "id": 110003,
    "isVariant": false,
    "isModExtend": false
  },
  {
    "icon": "zhuxianjuqing",
    "Difficulty": 0,
    "type": 1,
    "title": "achievementTitle110004",
    "desc": "achievementDesc110004",
    "count": 1,
    "value": "73328_73329",
    "condition": "0",
    "feature": 2419,
    "id": 110004,
    "isVariant": false,
    "isModExtend": false
  },
  {
    "icon": "zhuxianjuqing",
    "Difficulty": 0,
    "type": 1,
    "title": "achievementTitle110005",
    "desc": "achievementDesc110005",
    "count": 1,
    "value": "760622_760651_760782",
    "condition": "0",
    "feature": 2420,
    "id": 110005,
    "isVariant": false,
    "isModExtend": false
  },
  {
    "icon": "zhuxianjuqing",
    "Difficulty": 0,
    "type": 16,
    "title": "achievementTitle110006",
    "desc": "achievementDesc110006",
    "count": 1,
    "value": "159",
    "condition": "0",
    "feature": 2421,
    "id": 110006,
    "isVariant": false,
    "isModExtend": false
  },
  {
    "icon": "zhuxianjuqing",
    "Difficulty": 0,
    "type": 1,
    "title": "achievementTitle110051",
    "desc": "achievementDesc110051",
    "count": 1,
    "value": "2251002",
    "condition": "0",
    "feature": 0,
    "id": 110051,
    "isVariant": false,
    "isModExtend": false
  },
  {
    "icon": "zhuxianjuqing",
    "Difficulty": 0,
    "type": 1,
    "title": "achievementTitle110052",
    "desc": "achievementDesc110052",
    "count": 1,
    "value": "2250622",
    "condition": "0",
    "feature": 0,
    "id": 110052,
    "isVariant": false,
    "isModExtend": false
  },
  {
    "icon": "zhuxianjuqing",
    "Difficulty": 0,
    "type": 1,
    "title": "achievementTitle110053",
    "desc": "achievementDesc110053",
    "count": 1,
    "value": "2270009",
    "condition": "0",
    "feature": 0,
    "id": 110053,
    "isVariant": false,
    "isModExtend": false
  },
  {
    "icon": "zhuxianjuqing",
    "Difficulty": 0,
    "type": 17,
    "title": "achievementTitle110054",
    "desc": "achievementDesc110054",
    "count": 1,
    "value": "0",
    "condition": "0",
    "feature": 0,
    "id": 110054,
    "isVariant": false,
    "isModExtend": false
  },
  {
    "icon": "zhuxianjuqing",
    "Difficulty": 0,
    "type": 17,
    "title": "achievementTitle110055",
    "desc": "achievementDesc110055",
    "count": 1,
    "value": "0",
    "condition": "0",
    "feature": 0,
    "id": 110055,
    "isVariant": false,
    "isModExtend": false
  },
  {
    "icon": "zhuxianjuqing",
    "Difficulty": 0,
    "type": 1,
    "title": "achievementTitle110101",
    "desc": "achievementDesc110101",
    "count": 1,
    "value": "610663_610670",
    "condition": "0",
    "feature": 1429,
    "id": 110101,
    "isVariant": false,
    "isModExtend": false
  },
  {
    "icon": "zhuxianjuqing",
    "Difficulty": 0,
    "type": 1,
    "title": "achievementTitle110102",
    "desc": "achievementDesc110102",
    "count": 1,
    "value": "6002199_6002344_6002256_6002306_6002237",
    "condition": "0",
    "feature": 0,
    "id": 110102,
    "isVariant": false,
    "isModExtend": false
  },
  {
    "icon": "zhuxianjuqing",
    "Difficulty": 0,
    "type": 1,
    "title": "achievementTitle110103",
    "desc": "achievementDesc110103",
    "count": 1,
    "value": "60030512_60030532",
    "condition": "0",
    "feature": 0,
    "id": 110103,
    "isVariant": false,
    "isModExtend": false
  },
  {
    "icon": "zhuxianjuqing",
    "Difficulty": 0,
    "type": 1,
    "title": "achievementTitle110104",
    "desc": "achievementDesc110104",
    "count": 1,
    "value": "970115",
    "condition": "0",
    "feature": 0,
    "id": 110104,
    "isVariant": false,
    "isModExtend": false
  },
  {
    "icon": "zhuxianjuqing",
    "Difficulty": 0,
    "type": 1,
    "title": "achievementTitle110105",
    "desc": "achievementDesc110105",
    "count": 1,
    "value": "2000346_2000349",
    "condition": "0",
    "feature": 0,
    "id": 110105,
    "isVariant": false,
    "isModExtend": false
  },
  {
    "icon": "zhuxianjuqing",
    "Difficulty": 0,
    "type": 1,
    "title": "achievementTitle110106",
    "desc": "achievementDesc110106",
    "count": 1,
    "value": "2000363_2000366",
    "condition": "0",
    "feature": 0,
    "id": 110106,
    "isVariant": false,
    "isModExtend": false
  },
  {
    "icon": "zhuxianjuqing",
    "Difficulty": 0,
    "type": 1,
    "title": "achievementTitle110107",
    "desc": "achievementDesc110107",
    "count": 1,
    "value": "2002708",
    "condition": "0",
    "feature": 0,
    "id": 110107,
    "isVariant": false,
    "isModExtend": false
  },
  {
    "icon": "zhuxianjuqing",
    "Difficulty": 0,
    "type": 1,
    "title": "achievementTitle110108",
    "desc": "achievementDesc110108",
    "count": 1,
    "value": "2100475_2101312_2102606_2102257",
    "condition": "0",
    "feature": 0,
    "id": 110108,
    "isVariant": false,
    "isModExtend": false
  },
  {
    "icon": "jingjie",
    "Difficulty": 0,
    "type": 2,
    "title": "achievementTitle120001",
    "desc": "achievementDesc120001",
    "count": 1,
    "value": "2_0",
    "condition": "0",
    "feature": 0,
    "id": 120001,
    "isVariant": false,
    "isModExtend": false
  },
  {
    "icon": "jingjie",
    "Difficulty": 0,
    "type": 2,
    "title": "achievementTitle120002",
    "desc": "achievementDesc120002",
    "count": 1,
    "value": "3_0",
    "condition": "0",
    "feature": 0,
    "id": 120002,
    "isVariant": false,
    "isModExtend": false
  },
  {
    "icon": "jingjie",
    "Difficulty": 0,
    "type": 2,
    "title": "achievementTitle120003",
    "desc": "achievementDesc120003",
    "count": 1,
    "value": "4_0",
    "condition": "0",
    "feature": 0,
    "id": 120003,
    "isVariant": false,
    "isModExtend": false
  },
  {
    "icon": "jingjie",
    "Difficulty": 0,
    "type": 2,
    "title": "achievementTitle120004",
    "desc": "achievementDesc120004",
    "count": 1,
    "value": "5_0",
    "condition": "0",
    "feature": 0,
    "id": 120004,
    "isVariant": false,
    "isModExtend": false
  },
  {
    "icon": "jingjie",
    "Difficulty": 0,
    "type": 2,
    "title": "achievementTitle120005",
    "desc": "achievementDesc120005",
    "count": 1,
    "value": "6_0",
    "condition": "0",
    "feature": 0,
    "id": 120005,
    "isVariant": false,
    "isModExtend": false
  },
  {
    "icon": "jingjie",
    "Difficulty": 0,
    "type": 2,
    "title": "achievementTitle120006",
    "desc": "achievementDesc120006",
    "count": 1,
    "value": "7_0",
    "condition": "0",
    "feature": 0,
    "id": 120006,
    "isVariant": false,
    "isModExtend": false
  },
  {
    "icon": "jingjie",
    "Difficulty": 0,
    "type": 2,
    "title": "achievementTitle120007",
    "desc": "achievementDesc120007",
    "count": 1,
    "value": "8_0",
    "condition": "0",
    "feature": 0,
    "id": 120007,
    "isVariant": false,
    "isModExtend": false
  },
  {
    "icon": "jingjie",
    "Difficulty": 0,
    "type": 2,
    "title": "achievementTitle120008",
    "desc": "achievementDesc120008",
    "count": 1,
    "value": "9_0",
    "condition": "0",
    "feature": 0,
    "id": 120008,
    "isVariant": false,
    "isModExtend": false
  },
  {
    "icon": "jingjie",
    "Difficulty": 0,
    "type": 2,
    "title": "achievementTitle120009",
    "desc": "achievementDesc120009",
    "count": 1,
    "value": "10_0",
    "condition": "0",
    "feature": 0,
    "id": 120009,
    "isVariant": false,
    "isModExtend": false
  },
  {
    "icon": "jingjie",
    "Difficulty": 0,
    "type": 2,
    "title": "achievementTitle120101",
    "desc": "achievementDesc120101",
    "count": 1,
    "value": "2_5",
    "condition": "0",
    "feature": 2114,
    "id": 120101,
    "isVariant": false,
    "isModExtend": false
  },
  {
    "icon": "jingjie",
    "Difficulty": 0,
    "type": 2,
    "title": "achievementTitle120102",
    "desc": "achievementDesc120102",
    "count": 1,
    "value": "4_5",
    "condition": "0",
    "feature": 2115,
    "id": 120102,
    "isVariant": false,
    "isModExtend": false
  },
  {
    "icon": "jingjie",
    "Difficulty": 0,
    "type": 2,
    "title": "achievementTitle120103",
    "desc": "achievementDesc120103",
    "count": 1,
    "value": "6_5",
    "condition": "0",
    "feature": 2116,
    "id": 120103,
    "isVariant": false,
    "isModExtend": false
  },
  {
    "icon": "sharen",
    "Difficulty": 0,
    "type": 3,
    "title": "achievementTitle130001",
    "desc": "achievementDesc130001",
    "count": 1,
    "value": "0",
    "condition": "0",
    "feature": 0,
    "id": 130001,
    "isVariant": false,
    "isModExtend": false
  },
  {
    "icon": "sharen",
    "Difficulty": 0,
    "type": 3,
    "title": "achievementTitle130002",
    "desc": "achievementDesc130002",
    "count": 10,
    "value": "0",
    "condition": "0",
    "feature": 0,
    "id": 130002,
    "isVariant": false,
    "isModExtend": false
  },
  {
    "icon": "sharen",
    "Difficulty": 0,
    "type": 3,
    "title": "achievementTitle130003",
    "desc": "achievementDesc130003",
    "count": 50,
    "value": "0",
    "condition": "0",
    "feature": 1305,
    "id": 130003,
    "isVariant": false,
    "isModExtend": false
  },
  {
    "icon": "npc",
    "Difficulty": 0,
    "type": 4,
    "title": "achievementTitle140001",
    "desc": "achievementDesc140001",
    "count": 1,
    "value": "11",
    "condition": "0",
    "feature": 0,
    "id": 140001,
    "isVariant": false,
    "isModExtend": false
  },
  {
    "icon": "npc",
    "Difficulty": 0,
    "type": 4,
    "title": "achievementTitle140002",
    "desc": "achievementDesc140002",
    "count": 1,
    "value": "10",
    "condition": "0",
    "feature": 0,
    "id": 140002,
    "isVariant": false,
    "isModExtend": false
  },
  {
    "icon": "npc",
    "Difficulty": 0,
    "type": 4,
    "title": "achievementTitle140003",
    "desc": "achievementDesc140003",
    "count": 1,
    "value": "5",
    "condition": "0",
    "feature": 0,
    "id": 140003,
    "isVariant": false,
    "isModExtend": false
  },
  {
    "icon": "npc",
    "Difficulty": 0,
    "type": 4,
    "title": "achievementTitle140004",
    "desc": "achievementDesc140004",
    "count": 1,
    "value": "6",
    "condition": "0",
    "feature": 0,
    "id": 140004,
    "isVariant": false,
    "isModExtend": false
  },
  {
    "icon": "npc",
    "Difficulty": 0,
    "type": 4,
    "title": "achievementTitle140005",
    "desc": "achievementDesc140005",
    "count": 1,
    "value": "7",
    "condition": "0",
    "feature": 0,
    "id": 140005,
    "isVariant": false,
    "isModExtend": false
  },
  {
    "icon": "npc",
    "Difficulty": 0,
    "type": 4,
    "title": "achievementTitle140006",
    "desc": "achievementDesc140006",
    "count": 10,
    "value": "101",
    "condition": "0",
    "feature": 0,
    "id": 140006,
    "isVariant": false,
    "isModExtend": false
  },
  {
    "icon": "npc",
    "Difficulty": 0,
    "type": 4,
    "title": "achievementTitle140007",
    "desc": "achievementDesc140007",
    "count": 20,
    "value": "101",
    "condition": "0",
    "feature": 0,
    "id": 140007,
    "isVariant": false,
    "isModExtend": false
  },
  {
    "icon": "npc",
    "Difficulty": 0,
    "type": 4,
    "title": "achievementTitle140008",
    "desc": "achievementDesc140008",
    "count": 1,
    "value": "104",
    "condition": "0",
    "feature": 0,
    "id": 140008,
    "isVariant": false,
    "isModExtend": false
  },
  {
    "icon": "npc",
    "Difficulty": 0,
    "type": 4,
    "title": "achievementTitle140009",
    "desc": "achievementDesc140009",
    "count": 10,
    "value": "104",
    "condition": "0",
    "feature": 0,
    "id": 140009,
    "isVariant": false,
    "isModExtend": false
  },
  {
    "icon": "npc",
    "Difficulty": 0,
    "type": 4,
    "title": "achievementTitle140010",
    "desc": "achievementDesc140010",
    "count": 1,
    "value": "8",
    "condition": "0",
    "feature": 0,
    "id": 140010,
    "isVariant": false,
    "isModExtend": false
  },
  {
    "icon": "npc",
    "Difficulty": 0,
    "type": 5,
    "title": "achievementTitle140101",
    "desc": "achievementDesc140101",
    "count": 1,
    "value": "104",
    "condition": "0",
    "feature": 0,
    "id": 140101,
    "isVariant": false,
    "isModExtend": false
  },
  {
    "icon": "npc",
    "Difficulty": 0,
    "type": 5,
    "title": "achievementTitle140102",
    "desc": "achievementDesc140102",
    "count": 10,
    "value": "104",
    "condition": "0",
    "feature": 2422,
    "id": 140102,
    "isVariant": false,
    "isModExtend": false
  },
  {
    "icon": "npc",
    "Difficulty": 0,
    "type": 12,
    "title": "achievementTitle140103",
    "desc": "achievementDesc140103",
    "count": 2,
    "value": "8_1|9_1",
    "condition": "0",
    "feature": 0,
    "id": 140103,
    "isVariant": false,
    "isModExtend": false
  },
  {
    "icon": "wafen",
    "Difficulty": 0,
    "type": 6,
    "title": "achievementTitle150001",
    "desc": "achievementDesc150001",
    "count": 10,
    "value": "51",
    "condition": "0",
    "feature": 0,
    "id": 150001,
    "isVariant": false,
    "isModExtend": false
  },
  {
    "icon": "npc",
    "Difficulty": 0,
    "type": 7,
    "title": "achievementTitle160001",
    "desc": "achievementDesc160001",
    "count": 10,
    "value": "UnitActionRoleStealItem",
    "condition": "0",
    "feature": 0,
    "id": 160001,
    "isVariant": false,
    "isModExtend": false
  },
  {
    "icon": "npc",
    "Difficulty": 0,
    "type": 7,
    "title": "achievementTitle160002",
    "desc": "achievementDesc160002",
    "count": 10,
    "value": "UnitActionRoleAttack",
    "condition": "0",
    "feature": 1106,
    "id": 160002,
    "isVariant": false,
    "isModExtend": false
  },
  {
    "icon": "npc",
    "Difficulty": 0,
    "type": 7,
    "title": "achievementTitle160003",
    "desc": "achievementDesc160003",
    "count": 10,
    "value": "UnitActionRoleGive",
    "condition": "0",
    "feature": 0,
    "id": 160003,
    "isVariant": false,
    "isModExtend": false
  },
  {
    "icon": "npc",
    "Difficulty": 0,
    "type": 7,
    "title": "achievementTitle160004",
    "desc": "achievementDesc160004",
    "count": 10,
    "value": "UnitActionRoleAskfor",
    "condition": "0",
    "feature": 0,
    "id": 160004,
    "isVariant": false,
    "isModExtend": false
  },
  {
    "icon": "npc",
    "Difficulty": 0,
    "type": 13,
    "title": "achievementTitle160005",
    "desc": "achievementDesc160005",
    "count": 10,
    "value": "UnitActionRoleDrill",
    "condition": "0",
    "feature": 0,
    "id": 160005,
    "isVariant": false,
    "isModExtend": false
  },
  {
    "icon": "npc",
    "Difficulty": 0,
    "type": 13,
    "title": "achievementTitle160006",
    "desc": "achievementDesc160006",
    "count": 10,
    "value": "UnitActionRoleTrains",
    "condition": "0",
    "feature": 0,
    "id": 160006,
    "isVariant": false,
    "isModExtend": false
  },
  {
    "icon": "npc",
    "Difficulty": 0,
    "type": 13,
    "title": "achievementTitle160007",
    "desc": "achievementDesc160007",
    "count": 10,
    "value": "UnitActionRoleDiscovery",
    "condition": "0",
    "feature": 0,
    "id": 160007,
    "isVariant": false,
    "isModExtend": false
  },
  {
    "icon": "npc",
    "Difficulty": 0,
    "type": 8,
    "title": "achievementTitle160101",
    "desc": "achievementDesc160101",
    "count": 10,
    "value": "0",
    "condition": "0",
    "feature": 0,
    "id": 160101,
    "isVariant": false,
    "isModExtend": false
  },
  {
    "icon": "huode",
    "Difficulty": 0,
    "type": 9,
    "title": "achievementTitle170001",
    "desc": "achievementDesc170001",
    "count": 1,
    "value": "6",
    "condition": "0",
    "feature": 0,
    "id": 170001,
    "isVariant": false,
    "isModExtend": false
  },
  {
    "icon": "huode",
    "Difficulty": 0,
    "type": 9,
    "title": "achievementTitle170002",
    "desc": "achievementDesc170002",
    "count": 1,
    "value": "5",
    "condition": "0",
    "feature": 0,
    "id": 170002,
    "isVariant": false,
    "isModExtend": false
  },
  {
    "icon": "huode",
    "Difficulty": 0,
    "type": 9,
    "title": "achievementTitle170003",
    "desc": "achievementDesc170003",
    "count": 1,
    "value": "3",
    "condition": "0",
    "feature": 0,
    "id": 170003,
    "isVariant": false,
    "isModExtend": false
  },
  {
    "icon": "huode",
    "Difficulty": 0,
    "type": 9,
    "title": "achievementTitle170004",
    "desc": "achievementDesc170004",
    "count": 1,
    "value": "2",
    "condition": "0",
    "feature": 0,
    "id": 170004,
    "isVariant": false,
    "isModExtend": false
  },
  {
    "icon": "huode",
    "Difficulty": 0,
    "type": 9,
    "title": "achievementTitle170005",
    "desc": "achievementDesc170005",
    "count": 1,
    "value": "1",
    "condition": "0",
    "feature": 0,
    "id": 170005,
    "isVariant": false,
    "isModExtend": false
  },
  {
    "icon": "huode",
    "Difficulty": 0,
    "type": 10,
    "title": "achievementTitle180001",
    "desc": "achievementDesc180001",
    "count": 500,
    "value": "reputation",
    "condition": "0",
    "feature": 0,
    "id": 180001,
    "isVariant": false,
    "isModExtend": false
  },
  {
    "icon": "huode",
    "Difficulty": 0,
    "type": 10,
    "title": "achievementTitle180002",
    "desc": "achievementDesc180002",
    "count": 1500,
    "value": "reputation",
    "condition": "0",
    "feature": 0,
    "id": 180002,
    "isVariant": false,
    "isModExtend": false
  },
  {
    "icon": "huode",
    "Difficulty": 0,
    "type": 10,
    "title": "achievementTitle180003",
    "desc": "achievementDesc180003",
    "count": 2500,
    "value": "reputation",
    "condition": "0",
    "feature": 0,
    "id": 180003,
    "isVariant": false,
    "isModExtend": false
  },
  {
    "icon": "huode",
    "Difficulty": 0,
    "type": 10,
    "title": "achievementTitle180004",
    "desc": "achievementDesc180004",
    "count": 5000,
    "value": "reputation",
    "condition": "0",
    "feature": 0,
    "id": 180004,
    "isVariant": false,
    "isModExtend": false
  },
  {
    "icon": "huode",
    "Difficulty": 0,
    "type": 10,
    "title": "achievementTitle180005",
    "desc": "achievementDesc180005",
    "count": 8000,
    "value": "reputation",
    "condition": "0",
    "feature": 0,
    "id": 180005,
    "isVariant": false,
    "isModExtend": false
  },
  {
    "icon": "huode",
    "Difficulty": 0,
    "type": 10,
    "title": "achievementTitle180006",
    "desc": "achievementDesc180006",
    "count": 15000,
    "value": "reputation",
    "condition": "0",
    "feature": 0,
    "id": 180006,
    "isVariant": false,
    "isModExtend": false
  },
  {
    "icon": "huode",
    "Difficulty": 0,
    "type": 10,
    "title": "achievementTitle180007",
    "desc": "achievementDesc180007",
    "count": 25000,
    "value": "reputation",
    "condition": "0",
    "feature": 0,
    "id": 180007,
    "isVariant": false,
    "isModExtend": false
  },
  {
    "icon": "huode",
    "Difficulty": 0,
    "type": 10,
    "title": "achievementTitle180008",
    "desc": "achievementDesc180008",
    "count": 40000,
    "value": "reputation",
    "condition": "0",
    "feature": 0,
    "id": 180008,
    "isVariant": false,
    "isModExtend": false
  },
  {
    "icon": "huode",
    "Difficulty": 0,
    "type": 10,
    "title": "achievementTitle180009",
    "desc": "achievementDesc180009",
    "count": 60000,
    "value": "reputation",
    "condition": "0",
    "feature": 0,
    "id": 180009,
    "isVariant": false,
    "isModExtend": false
  },
  {
    "icon": "huode",
    "Difficulty": 0,
    "type": 10,
    "title": "achievementTitle180010",
    "desc": "achievementDesc180010",
    "count": 100000,
    "value": "reputation",
    "condition": "0",
    "feature": 0,
    "id": 180010,
    "isVariant": false,
    "isModExtend": false
  },
  {
    "icon": "huode",
    "Difficulty": 0,
    "type": 10,
    "title": "achievementTitle180011",
    "desc": "achievementDesc180011",
    "count": 450,
    "value": "beauty",
    "condition": "0",
    "feature": 2107,
    "id": 180011,
    "isVariant": false,
    "isModExtend": false
  },
  {
    "icon": "huode",
    "Difficulty": 0,
    "type": 10,
    "title": "achievementTitle180012",
    "desc": "achievementDesc180012",
    "count": 650,
    "value": "beauty",
    "condition": "0",
    "feature": 1006,
    "id": 180012,
    "isVariant": false,
    "isModExtend": false
  },
  {
    "icon": "huode",
    "Difficulty": 0,
    "type": 14,
    "title": "achievementTitle180013",
    "desc": "achievementDesc180013",
    "count": -120,
    "value": "beauty",
    "condition": "0",
    "feature": 0,
    "id": 180013,
    "isVariant": false,
    "isModExtend": false
  },
  {
    "icon": "huode",
    "Difficulty": 0,
    "type": 10,
    "title": "achievementTitle180014",
    "desc": "achievementDesc180014",
    "count": 100,
    "value": "basBlade",
    "condition": "stand_1",
    "feature": 1408,
    "id": 180014,
    "isVariant": false,
    "isModExtend": false
  },
  {
    "icon": "huode",
    "Difficulty": 0,
    "type": 10,
    "title": "achievementTitle180015",
    "desc": "achievementDesc180015",
    "count": 100,
    "value": "basSpear",
    "condition": "stand_1",
    "feature": 1409,
    "id": 180015,
    "isVariant": false,
    "isModExtend": false
  },
  {
    "icon": "huode",
    "Difficulty": 0,
    "type": 10,
    "title": "achievementTitle180016",
    "desc": "achievementDesc180016",
    "count": 100,
    "value": "basSword",
    "condition": "stand_1",
    "feature": 1407,
    "id": 180016,
    "isVariant": false,
    "isModExtend": false
  },
  {
    "icon": "huode",
    "Difficulty": 0,
    "type": 10,
    "title": "achievementTitle180017",
    "desc": "achievementDesc180017",
    "count": 100,
    "value": "basFist",
    "condition": "stand_1",
    "feature": 1410,
    "id": 180017,
    "isVariant": false,
    "isModExtend": false
  },
  {
    "icon": "huode",
    "Difficulty": 0,
    "type": 10,
    "title": "achievementTitle180018",
    "desc": "achievementDesc180018",
    "count": 100,
    "value": "basPalm",
    "condition": "stand_1",
    "feature": 1412,
    "id": 180018,
    "isVariant": false,
    "isModExtend": false
  },
  {
    "icon": "huode",
    "Difficulty": 0,
    "type": 10,
    "title": "achievementTitle180019",
    "desc": "achievementDesc180019",
    "count": 100,
    "value": "basFinger",
    "condition": "stand_1",
    "feature": 1411,
    "id": 180019,
    "isVariant": false,
    "isModExtend": false
  },
  {
    "icon": "huode",
    "Difficulty": 0,
    "type": 10,
    "title": "achievementTitle180020",
    "desc": "achievementDesc180020",
    "count": 100,
    "value": "basBlade",
    "condition": "stand_2",
    "feature": 1402,
    "id": 180020,
    "isVariant": false,
    "isModExtend": false
  },
  {
    "icon": "huode",
    "Difficulty": 0,
    "type": 10,
    "title": "achievementTitle180021",
    "desc": "achievementDesc180021",
    "count": 100,
    "value": "basSpear",
    "condition": "stand_2",
    "feature": 1403,
    "id": 180021,
    "isVariant": false,
    "isModExtend": false
  },
  {
    "icon": "huode",
    "Difficulty": 0,
    "type": 10,
    "title": "achievementTitle180022",
    "desc": "achievementDesc180022",
    "count": 100,
    "value": "basSword",
    "condition": "stand_2",
    "feature": 1401,
    "id": 180022,
    "isVariant": false,
    "isModExtend": false
  },
  {
    "icon": "huode",
    "Difficulty": 0,
    "type": 10,
    "title": "achievementTitle180023",
    "desc": "achievementDesc180023",
    "count": 100,
    "value": "basFist",
    "condition": "stand_2",
    "feature": 1404,
    "id": 180023,
    "isVariant": false,
    "isModExtend": false
  },
  {
    "icon": "huode",
    "Difficulty": 0,
    "type": 10,
    "title": "achievementTitle180024",
    "desc": "achievementDesc180024",
    "count": 100,
    "value": "basPalm",
    "condition": "stand_2",
    "feature": 1406,
    "id": 180024,
    "isVariant": false,
    "isModExtend": false
  },
  {
    "icon": "huode",
    "Difficulty": 0,
    "type": 10,
    "title": "achievementTitle180025",
    "desc": "achievementDesc180025",
    "count": 100,
    "value": "basFinger",
    "condition": "stand_2",
    "feature": 1405,
    "id": 180025,
    "isVariant": false,
    "isModExtend": false
  },
  {
    "icon": "huode",
    "Difficulty": 0,
    "type": 10,
    "title": "achievementTitle180026",
    "desc": "achievementDesc180026",
    "count": 100,
    "value": "basFire",
    "condition": "0",
    "feature": 2203,
    "id": 180026,
    "isVariant": false,
    "isModExtend": false
  },
  {
    "icon": "huode",
    "Difficulty": 0,
    "type": 10,
    "title": "achievementTitle180027",
    "desc": "achievementDesc180027",
    "count": 100,
    "value": "basFroze",
    "condition": "0",
    "feature": 2205,
    "id": 180027,
    "isVariant": false,
    "isModExtend": false
  },
  {
    "icon": "huode",
    "Difficulty": 0,
    "type": 10,
    "title": "achievementTitle180028",
    "desc": "achievementDesc180028",
    "count": 100,
    "value": "basThunder",
    "condition": "0",
    "feature": 2201,
    "id": 180028,
    "isVariant": false,
    "isModExtend": false
  },
  {
    "icon": "huode",
    "Difficulty": 0,
    "type": 10,
    "title": "achievementTitle180029",
    "desc": "achievementDesc180029",
    "count": 100,
    "value": "basWind",
    "condition": "0",
    "feature": 2207,
    "id": 180029,
    "isVariant": false,
    "isModExtend": false
  },
  {
    "icon": "huode",
    "Difficulty": 0,
    "type": 10,
    "title": "achievementTitle180030",
    "desc": "achievementDesc180030",
    "count": 100,
    "value": "basEarth",
    "condition": "0",
    "feature": 2209,
    "id": 180030,
    "isVariant": false,
    "isModExtend": false
  },
  {
    "icon": "huode",
    "Difficulty": 0,
    "type": 10,
    "title": "achievementTitle180031",
    "desc": "achievementDesc180031",
    "count": 100,
    "value": "basWood",
    "condition": "0",
    "feature": 2211,
    "id": 180031,
    "isVariant": false,
    "isModExtend": false
  },
  {
    "icon": "huode",
    "Difficulty": 0,
    "type": 10,
    "title": "achievementTitle180032",
    "desc": "achievementDesc180032",
    "count": 130,
    "value": "basFire",
    "condition": "0",
    "feature": 2204,
    "id": 180032,
    "isVariant": false,
    "isModExtend": false
  },
  {
    "icon": "huode",
    "Difficulty": 0,
    "type": 10,
    "title": "achievementTitle180033",
    "desc": "achievementDesc180033",
    "count": 130,
    "value": "basFroze",
    "condition": "0",
    "feature": 2206,
    "id": 180033,
    "isVariant": false,
    "isModExtend": false
  },
  {
    "icon": "huode",
    "Difficulty": 0,
    "type": 10,
    "title": "achievementTitle180034",
    "desc": "achievementDesc180034",
    "count": 130,
    "value": "basThunder",
    "condition": "0",
    "feature": 2202,
    "id": 180034,
    "isVariant": false,
    "isModExtend": false
  },
  {
    "icon": "huode",
    "Difficulty": 0,
    "type": 10,
    "title": "achievementTitle180035",
    "desc": "achievementDesc180035",
    "count": 130,
    "value": "basWind",
    "condition": "0",
    "feature": 2208,
    "id": 180035,
    "isVariant": false,
    "isModExtend": false
  },
  {
    "icon": "huode",
    "Difficulty": 0,
    "type": 10,
    "title": "achievementTitle180036",
    "desc": "achievementDesc180036",
    "count": 130,
    "value": "basEarth",
    "condition": "0",
    "feature": 2210,
    "id": 180036,
    "isVariant": false,
    "isModExtend": false
  },
  {
    "icon": "huode",
    "Difficulty": 0,
    "type": 10,
    "title": "achievementTitle180037",
    "desc": "achievementDesc180037",
    "count": 130,
    "value": "basWood",
    "condition": "0",
    "feature": 2212,
    "id": 180037,
    "isVariant": false,
    "isModExtend": false
  },
  {
    "icon": "huode",
    "Difficulty": 0,
    "type": 15,
    "title": "achievementTitle180038",
    "desc": "achievementDesc180038",
    "count": 300,
    "value": "basBlade_50|basSpear_50|basSword_50|basFist_50|basPalm_50|basFinger_50",
    "condition": "0",
    "feature": 2002,
    "id": 180038,
    "isVariant": false,
    "isModExtend": false
  },
  {
    "icon": "huode",
    "Difficulty": 0,
    "type": 10,
    "title": "achievementTitle180039",
    "desc": "achievementDesc180039",
    "count": 50,
    "value": "basMgAll",
    "condition": "0",
    "feature": 2003,
    "id": 180039,
    "isVariant": false,
    "isModExtend": false
  },
  {
    "icon": "huode",
    "Difficulty": 0,
    "type": 11,
    "title": "achievementTitle190001",
    "desc": "achievementDesc190001",
    "count": 1000,
    "value": "10001",
    "condition": "0",
    "feature": 0,
    "id": 190001,
    "isVariant": false,
    "isModExtend": false
  },
  {
    "icon": "huode",
    "Difficulty": 0,
    "type": 11,
    "title": "achievementTitle190002",
    "desc": "achievementDesc190002",
    "count": 2000,
    "value": "10001",
    "condition": "0",
    "feature": 0,
    "id": 190002,
    "isVariant": false,
    "isModExtend": false
  },
  {
    "icon": "huode",
    "Difficulty": 0,
    "type": 11,
    "title": "achievementTitle190003",
    "desc": "achievementDesc190003",
    "count": 5000,
    "value": "10001",
    "condition": "0",
    "feature": 0,
    "id": 190003,
    "isVariant": false,
    "isModExtend": false
  },
  {
    "icon": "huode",
    "Difficulty": 0,
    "type": 11,
    "title": "achievementTitle190004",
    "desc": "achievementDesc190004",
    "count": 10000,
    "value": "10001",
    "condition": "0",
    "feature": 0,
    "id": 190004,
    "isVariant": false,
    "isModExtend": false
  },
  {
    "icon": "huode",
    "Difficulty": 0,
    "type": 11,
    "title": "achievementTitle190005",
    "desc": "achievementDesc190005",
    "count": 20000,
    "value": "10001",
    "condition": "0",
    "feature": 0,
    "id": 190005,
    "isVariant": false,
    "isModExtend": false
  },
  {
    "icon": "huode",
    "Difficulty": 0,
    "type": 11,
    "title": "achievementTitle190006",
    "desc": "achievementDesc190006",
    "count": 50000,
    "value": "10001",
    "condition": "0",
    "feature": 0,
    "id": 190006,
    "isVariant": false,
    "isModExtend": false
  },
  {
    "icon": "huode",
    "Difficulty": 0,
    "type": 11,
    "title": "achievementTitle190007",
    "desc": "achievementDesc190007",
    "count": 100000,
    "value": "10001",
    "condition": "0",
    "feature": 0,
    "id": 190007,
    "isVariant": false,
    "isModExtend": false
  },
  {
    "icon": "huode",
    "Difficulty": 0,
    "type": 11,
    "title": "achievementTitle190008",
    "desc": "achievementDesc190008",
    "count": 200000,
    "value": "10001",
    "condition": "0",
    "feature": 0,
    "id": 190008,
    "isVariant": false,
    "isModExtend": false
  },
  {
    "icon": "huode",
    "Difficulty": 0,
    "type": 11,
    "title": "achievementTitle190009",
    "desc": "achievementDesc190009",
    "count": 500000,
    "value": "10001",
    "condition": "0",
    "feature": 0,
    "id": 190009,
    "isVariant": false,
    "isModExtend": false
  },
  {
    "icon": "huode",
    "Difficulty": 0,
    "type": 11,
    "title": "achievementTitle190010",
    "desc": "achievementDesc190010",
    "count": 1000000,
    "value": "10001",
    "condition": "0",
    "feature": 1911,
    "id": 190010,
    "isVariant": false,
    "isModExtend": false
  },
  {
    "icon": "huode",
    "Difficulty": 0,
    "type": 11,
    "title": "achievementTitle190011",
    "desc": "achievementDesc190011",
    "count": 100,
    "value": "10011",
    "condition": "0",
    "feature": 0,
    "id": 190011,
    "isVariant": false,
    "isModExtend": false
  },
  {
    "icon": "huode",
    "Difficulty": 0,
    "type": 11,
    "title": "achievementTitle190012",
    "desc": "achievementDesc190012",
    "count": 200,
    "value": "10011",
    "condition": "0",
    "feature": 0,
    "id": 190012,
    "isVariant": false,
    "isModExtend": false
  },
  {
    "icon": "huode",
    "Difficulty": 0,
    "type": 11,
    "title": "achievementTitle190013",
    "desc": "achievementDesc190013",
    "count": 500,
    "value": "10011",
    "condition": "0",
    "feature": 0,
    "id": 190013,
    "isVariant": false,
    "isModExtend": false
  },
  {
    "icon": "huode",
    "Difficulty": 0,
    "type": 11,
    "title": "achievementTitle190014",
    "desc": "achievementDesc190014",
    "count": 1000,
    "value": "10011",
    "condition": "0",
    "feature": 0,
    "id": 190014,
    "isVariant": false,
    "isModExtend": false
  },
  {
    "icon": "huode",
    "Difficulty": 0,
    "type": 11,
    "title": "achievementTitle190015",
    "desc": "achievementDesc190015",
    "count": 2000,
    "value": "10011",
    "condition": "0",
    "feature": 0,
    "id": 190015,
    "isVariant": false,
    "isModExtend": false
  },
  {
    "icon": "huode",
    "Difficulty": 0,
    "type": 11,
    "title": "achievementTitle190016",
    "desc": "achievementDesc190016",
    "count": 5000,
    "value": "10011",
    "condition": "0",
    "feature": 0,
    "id": 190016,
    "isVariant": false,
    "isModExtend": false
  },
  {
    "icon": "huode",
    "Difficulty": 0,
    "type": 11,
    "title": "achievementTitle190017",
    "desc": "achievementDesc190017",
    "count": 10000,
    "value": "10011",
    "condition": "0",
    "feature": 0,
    "id": 190017,
    "isVariant": false,
    "isModExtend": false
  },
  {
    "icon": "huode",
    "Difficulty": 0,
    "type": 11,
    "title": "achievementTitle190018",
    "desc": "achievementDesc190018",
    "count": 20000,
    "value": "10011",
    "condition": "0",
    "feature": 0,
    "id": 190018,
    "isVariant": false,
    "isModExtend": false
  },
  {
    "icon": "huode",
    "Difficulty": 0,
    "type": 11,
    "title": "achievementTitle190019",
    "desc": "achievementDesc190019",
    "count": 50000,
    "value": "10011",
    "condition": "0",
    "feature": 0,
    "id": 190019,
    "isVariant": false,
    "isModExtend": false
  },
  {
    "icon": "huode",
    "Difficulty": 0,
    "type": 11,
    "title": "achievementTitle190020",
    "desc": "achievementDesc190020",
    "count": 100000,
    "value": "10011",
    "condition": "0",
    "feature": 0,
    "id": 190020,
    "isVariant": false,
    "isModExtend": false
  },
  {
    "icon": "canku_jingjie",
    "Difficulty": 5,
    "type": 2,
    "title": "achievementTitle200001",
    "desc": "achievementDesc200001",
    "count": 1,
    "value": "2_0",
    "condition": "0",
    "feature": 0,
    "id": 200001,
    "isVariant": false,
    "isModExtend": false
  },
  {
    "icon": "canku_jingjie",
    "Difficulty": 5,
    "type": 2,
    "title": "achievementTitle200002",
    "desc": "achievementDesc200002",
    "count": 1,
    "value": "3_0",
    "condition": "0",
    "feature": 0,
    "id": 200002,
    "isVariant": false,
    "isModExtend": false
  },
  {
    "icon": "canku_jingjie",
    "Difficulty": 5,
    "type": 2,
    "title": "achievementTitle200003",
    "desc": "achievementDesc200003",
    "count": 1,
    "value": "4_0",
    "condition": "0",
    "feature": 0,
    "id": 200003,
    "isVariant": false,
    "isModExtend": false
  },
  {
    "icon": "canku_jingjie",
    "Difficulty": 5,
    "type": 2,
    "title": "achievementTitle200004",
    "desc": "achievementDesc200004",
    "count": 1,
    "value": "5_0",
    "condition": "0",
    "feature": 0,
    "id": 200004,
    "isVariant": false,
    "isModExtend": false
  },
  {
    "icon": "canku_jingjie",
    "Difficulty": 5,
    "type": 2,
    "title": "achievementTitle200005",
    "desc": "achievementDesc200005",
    "count": 1,
    "value": "6_0",
    "condition": "0",
    "feature": 0,
    "id": 200005,
    "isVariant": false,
    "isModExtend": false
  },
  {
    "icon": "canku_jingjie",
    "Difficulty": 5,
    "type": 2,
    "title": "achievementTitle200006",
    "desc": "achievementDesc200006",
    "count": 1,
    "value": "7_0",
    "condition": "0",
    "feature": 0,
    "id": 200006,
    "isVariant": false,
    "isModExtend": false
  },
  {
    "icon": "canku_jingjie",
    "Difficulty": 5,
    "type": 2,
    "title": "achievementTitle200007",
    "desc": "achievementDesc200007",
    "count": 1,
    "value": "8_0",
    "condition": "0",
    "feature": 0,
    "id": 200007,
    "isVariant": false,
    "isModExtend": false
  },
  {
    "icon": "canku_jingjie",
    "Difficulty": 5,
    "type": 2,
    "title": "achievementTitle200008",
    "desc": "achievementDesc200008",
    "count": 1,
    "value": "9_0",
    "condition": "0",
    "feature": 0,
    "id": 200008,
    "isVariant": false,
    "isModExtend": false
  },
  {
    "icon": "canku_jingjie",
    "Difficulty": 5,
    "type": 2,
    "title": "achievementTitle200009",
    "desc": "achievementDesc200009",
    "count": 1,
    "value": "10_0",
    "condition": "0",
    "feature": 0,
    "id": 200009,
    "isVariant": false,
    "isModExtend": false
  },
  {
    "icon": "canku_fuben",
    "Difficulty": 5,
    "type": 16,
    "title": "achievementTitle210001",
    "desc": "achievementDesc210001",
    "count": 1,
    "value": "6101",
    "condition": "0",
    "feature": 0,
    "id": 210001,
    "isVariant": false,
    "isModExtend": false
  },
  {
    "icon": "canku_fuben",
    "Difficulty": 5,
    "type": 16,
    "title": "achievementTitle210002",
    "desc": "achievementDesc210002",
    "count": 1,
    "value": "6102",
    "condition": "0",
    "feature": 0,
    "id": 210002,
    "isVariant": false,
    "isModExtend": false
  },
  {
    "icon": "canku_fuben",
    "Difficulty": 5,
    "type": 16,
    "title": "achievementTitle210003",
    "desc": "achievementDesc210003",
    "count": 1,
    "value": "6103",
    "condition": "0",
    "feature": 0,
    "id": 210003,
    "isVariant": false,
    "isModExtend": false
  },
  {
    "icon": "canku_fuben",
    "Difficulty": 5,
    "type": 16,
    "title": "achievementTitle210004",
    "desc": "achievementDesc210004",
    "count": 1,
    "value": "6104",
    "condition": "0",
    "feature": 0,
    "id": 210004,
    "isVariant": false,
    "isModExtend": false
  },
  {
    "icon": "canku_fuben",
    "Difficulty": 5,
    "type": 16,
    "title": "achievementTitle210005",
    "desc": "achievementDesc210005",
    "count": 1,
    "value": "6105",
    "condition": "0",
    "feature": 0,
    "id": 210005,
    "isVariant": false,
    "isModExtend": false
  },
  {
    "icon": "canku_fuben",
    "Difficulty": 5,
    "type": 16,
    "title": "achievementTitle210006",
    "desc": "achievementDesc210006",
    "count": 1,
    "value": "6106",
    "condition": "0",
    "feature": 0,
    "id": 210006,
    "isVariant": false,
    "isModExtend": false
  },
  {
    "icon": "canku_fuben",
    "Difficulty": 5,
    "type": 16,
    "title": "achievementTitle210007",
    "desc": "achievementDesc210007",
    "count": 1,
    "value": "6107",
    "condition": "0",
    "feature": 0,
    "id": 210007,
    "isVariant": false,
    "isModExtend": false
  },
  {
    "icon": "canku_fuben",
    "Difficulty": 5,
    "type": 16,
    "title": "achievementTitle210008",
    "desc": "achievementDesc210008",
    "count": 1,
    "value": "6108",
    "condition": "0",
    "feature": 0,
    "id": 210008,
    "isVariant": false,
    "isModExtend": false
  },
  {
    "icon": "canku_fuben",
    "Difficulty": 5,
    "type": 16,
    "title": "achievementTitle210009",
    "desc": "achievementDesc210009",
    "count": 1,
    "value": "6109",
    "condition": "0",
    "feature": 0,
    "id": 210009,
    "isVariant": false,
    "isModExtend": false
  },
  {
    "icon": "canku_sharen",
    "Difficulty": 0,
    "type": 17,
    "title": "achievementTitle300001",
    "desc": "achievementDesc300001",
    "count": 0,
    "value": "0",
    "condition": "0",
    "feature": 0,
    "id": 300001,
    "isVariant": false,
    "isModExtend": false
  },
  {
    "icon": "canku_sharen",
    "Difficulty": 0,
    "type": 17,
    "title": "achievementTitle300002",
    "desc": "achievementDesc300002",
    "count": 0,
    "value": "0",
    "condition": "0",
    "feature": 0,
    "id": 300002,
    "isVariant": false,
    "isModExtend": false
  },
  {
    "icon": "jingjie",
    "Difficulty": 0,
    "type": 17,
    "title": "achievementTitle300003",
    "desc": "achievementDesc300003",
    "count": 0,
    "value": "0",
    "condition": "0",
    "feature": 0,
    "id": 300003,
    "isVariant": false,
    "isModExtend": false
  },
  {
    "icon": "npc",
    "Difficulty": 0,
    "type": 17,
    "title": "achievementTitle300004",
    "desc": "achievementDesc300004",
    "count": 0,
    "value": "0",
    "condition": "0",
    "feature": 0,
    "id": 300004,
    "isVariant": false,
    "isModExtend": false
  },
  {
    "icon": "canku_sharen",
    "Difficulty": 0,
    "type": 17,
    "title": "achievementTitle300005",
    "desc": "achievementDesc300005",
    "count": 0,
    "value": "0",
    "condition": "0",
    "feature": 0,
    "id": 300005,
    "isVariant": false,
    "isModExtend": false
  },
  {
    "icon": "canku_zhuxianjuqing",
    "Difficulty": 0,
    "type": 17,
    "title": "achievementTitle300006",
    "desc": "achievementDesc300006",
    "count": 0,
    "value": "0",
    "condition": "0",
    "feature": 0,
    "id": 300006,
    "isVariant": false,
    "isModExtend": false
  },
  {
    "icon": "canku_zhuxianjuqing",
    "Difficulty": 0,
    "type": 17,
    "title": "achievementTitle300007",
    "desc": "achievementDesc300007",
    "count": 0,
    "value": "0",
    "condition": "0",
    "feature": 0,
    "id": 300007,
    "isVariant": false,
    "isModExtend": false
  },
  {
    "icon": "npc",
    "Difficulty": 0,
    "type": 17,
    "title": "achievementTitle300008",
    "desc": "achievementDesc300008",
    "count": 0,
    "value": "0",
    "condition": "0",
    "feature": 0,
    "id": 300008,
    "isVariant": false,
    "isModExtend": false
  },
  {
    "icon": "canku_sharen",
    "Difficulty": 0,
    "type": 17,
    "title": "achievementTitle300009",
    "desc": "achievementDesc300009",
    "count": 0,
    "value": "0",
    "condition": "0",
    "feature": 0,
    "id": 300009,
    "isVariant": false,
    "isModExtend": false
  },
  {
    "icon": "npc",
    "Difficulty": 0,
    "type": 17,
    "title": "achievementTitle300011",
    "desc": "achievementDesc300011",
    "count": 0,
    "value": "0",
    "condition": "0",
    "feature": 0,
    "id": 300011,
    "isVariant": false,
    "isModExtend": false
  },
  {
    "icon": "npc",
    "Difficulty": 0,
    "type": 17,
    "title": "achievementTitle300012",
    "desc": "achievementDesc300012",
    "count": 0,
    "value": "0",
    "condition": "0",
    "feature": 0,
    "id": 300012,
    "isVariant": false,
    "isModExtend": false
  },
  {
    "icon": "npc",
    "Difficulty": 0,
    "type": 17,
    "title": "achievementTitle300013",
    "desc": "achievementDesc300013",
    "count": 0,
    "value": "0",
    "condition": "0",
    "feature": 0,
    "id": 300013,
    "isVariant": false,
    "isModExtend": false
  },
  {
    "icon": "npc",
    "Difficulty": 0,
    "type": 17,
    "title": "achievementTitle300014",
    "desc": "achievementDesc300014",
    "count": 0,
    "value": "0",
    "condition": "0",
    "feature": 0,
    "id": 300014,
    "isVariant": false,
    "isModExtend": false
  },
  {
    "icon": "npc",
    "Difficulty": 0,
    "type": 17,
    "title": "achievementTitle300015",
    "desc": "achievementDesc300015",
    "count": 0,
    "value": "0",
    "condition": "0",
    "feature": 0,
    "id": 300015,
    "isVariant": false,
    "isModExtend": false
  },
  {
    "icon": "npc",
    "Difficulty": 0,
    "type": 17,
    "title": "achievementTitle300016",
    "desc": "achievementDesc300016",
    "count": 0,
    "value": "0",
    "condition": "0",
    "feature": 0,
    "id": 300016,
    "isVariant": false,
    "isModExtend": false
  },
  {
    "icon": "canku_wafen",
    "Difficulty": 0,
    "type": 17,
    "title": "achievementTitle300017",
    "desc": "achievementDesc300017",
    "count": 0,
    "value": "0",
    "condition": "0",
    "feature": 0,
    "id": 300017,
    "isVariant": false,
    "isModExtend": false
  },
  {
    "icon": "npc",
    "Difficulty": 0,
    "type": 17,
    "title": "achievementTitle300019",
    "desc": "achievementDesc300019",
    "count": 0,
    "value": "0",
    "condition": "0",
    "feature": 0,
    "id": 300019,
    "isVariant": false,
    "isModExtend": false
  },
  {
    "icon": "npc",
    "Difficulty": 0,
    "type": 17,
    "title": "achievementTitle300020",
    "desc": "achievementDesc300020",
    "count": 0,
    "value": "0",
    "condition": "0",
    "feature": 0,
    "id": 300020,
    "isVariant": false,
    "isModExtend": false
  },
  {
    "icon": "npc",
    "Difficulty": 0,
    "type": 17,
    "title": "achievementTitle300021",
    "desc": "achievementDesc300021",
    "count": 0,
    "value": "0",
    "condition": "0",
    "feature": 0,
    "id": 300021,
    "isVariant": false,
    "isModExtend": false
  },
  {
    "icon": "npc",
    "Difficulty": 0,
    "type": 17,
    "title": "achievementTitle300022",
    "desc": "achievementDesc300022",
    "count": 0,
    "value": "0",
    "condition": "0",
    "feature": 0,
    "id": 300022,
    "isVariant": false,
    "isModExtend": false
  },
  {
    "icon": "npc",
    "Difficulty": 0,
    "type": 17,
    "title": "achievementTitle300023",
    "desc": "achievementDesc300023",
    "count": 0,
    "value": "0",
    "condition": "0",
    "feature": 0,
    "id": 300023,
    "isVariant": false,
    "isModExtend": false
  },
  {
    "icon": "canku_sharen",
    "Difficulty": 0,
    "type": 17,
    "title": "achievementTitle300024",
    "desc": "achievementDesc300024",
    "count": 0,
    "value": "0",
    "condition": "0",
    "feature": 0,
    "id": 300024,
    "isVariant": false,
    "isModExtend": false
  },
  {
    "icon": "npc",
    "Difficulty": 0,
    "type": 17,
    "title": "achievementTitle300025",
    "desc": "achievementDesc300025",
    "count": 0,
    "value": "0",
    "condition": "0",
    "feature": 0,
    "id": 300025,
    "isVariant": false,
    "isModExtend": false
  },
  {
    "icon": "npc",
    "Difficulty": 0,
    "type": 17,
    "title": "achievementTitle300026",
    "desc": "achievementDesc300026",
    "count": 0,
    "value": "0",
    "condition": "0",
    "feature": 0,
    "id": 300026,
    "isVariant": false,
    "isModExtend": false
  },
  {
    "icon": "npc",
    "Difficulty": 0,
    "type": 17,
    "title": "achievementTitle300027",
    "desc": "achievementDesc300027",
    "count": 0,
    "value": "0",
    "condition": "0",
    "feature": 0,
    "id": 300027,
    "isVariant": false,
    "isModExtend": false
  },
  {
    "icon": "npc",
    "Difficulty": 0,
    "type": 17,
    "title": "achievementTitle300028",
    "desc": "achievementDesc300028",
    "count": 0,
    "value": "0",
    "condition": "0",
    "feature": 0,
    "id": 300028,
    "isVariant": false,
    "isModExtend": false
  },
  {
    "icon": "canku_sharen",
    "Difficulty": 0,
    "type": 17,
    "title": "achievementTitle300029",
    "desc": "achievementDesc300029",
    "count": 0,
    "value": "0",
    "condition": "0",
    "feature": 0,
    "id": 300029,
    "isVariant": false,
    "isModExtend": false
  },
  {
    "icon": "canku_fuben",
    "Difficulty": 0,
    "type": 17,
    "title": "achievementTitle300030",
    "desc": "achievementDesc300030",
    "count": 0,
    "value": "0",
    "condition": "0",
    "feature": 0,
    "id": 300030,
    "isVariant": false,
    "isModExtend": false
  },
  {
    "icon": "canku_sharen",
    "Difficulty": 0,
    "type": 17,
    "title": "achievementTitle300031",
    "desc": "achievementDesc300031",
    "count": 0,
    "value": "0",
    "condition": "0",
    "feature": 0,
    "id": 300031,
    "isVariant": false,
    "isModExtend": false
  },
  {
    "icon": "canku_fuben",
    "Difficulty": 0,
    "type": 17,
    "title": "achievementTitle300032",
    "desc": "achievementDesc300032",
    "count": 0,
    "value": "0",
    "condition": "0",
    "feature": 0,
    "id": 300032,
    "isVariant": false,
    "isModExtend": false
  },
  {
    "icon": "canku_fuben",
    "Difficulty": 0,
    "type": 17,
    "title": "achievementTitle300033",
    "desc": "achievementDesc300033",
    "count": 0,
    "value": "0",
    "condition": "0",
    "feature": 0,
    "id": 300033,
    "isVariant": false,
    "isModExtend": false
  },
  {
    "icon": "canku_huode",
    "Difficulty": 0,
    "type": 17,
    "title": "achievementTitle300036",
    "desc": "achievementDesc300036",
    "count": 0,
    "value": "0",
    "condition": "0",
    "feature": 0,
    "id": 300036,
    "isVariant": false,
    "isModExtend": false
  }
]