[
  {
    "name": "effectClassName2101",
    "id": 2101,
    "isVariant": false,
    "isModExtend": false
  },
  {
    "name": "effectClassName2601",
    "id": 2601,
    "isVariant": false,
    "isModExtend": false
  },
  {
    "name": "effectClassName1001",
    "id": 1001,
    "isVariant": false,
    "isModExtend": false
  },
  {
    "name": "effectClassName1002",
    "id": 1002,
    "isVariant": false,
    "isModExtend": false
  },
  {
    "name": "effectClassName4001",
    "id": 4001,
    "isVariant": false,
    "isModExtend": false
  },
  {
    "name": "effectClassName4002",
    "id": 4002,
    "isVariant": false,
    "isModExtend": false
  },
  {
    "name": "effectClassName4003",
    "id": 4003,
    "isVariant": false,
    "isModExtend": false
  },
  {
    "name": "effectClassName4004",
    "id": 4004,
    "isVariant": false,
    "isModExtend": false
  },
  {
    "name": "effectClassName4005",
    "id": 4005,
    "isVariant": false,
    "isModExtend": false
  },
  {
    "name": "effectClassName4006",
    "id": 4006,
    "isVariant": false,
    "isModExtend": false
  },
  {
    "name": "effectClassName4007",
    "id": 4007,
    "isVariant": false,
    "isModExtend": false
  },
  {
    "name": "effectClassName4008",
    "id": 4008,
    "isVariant": false,
    "isModExtend": false
  },
  {
    "name": "effectClassName4009",
    "id": 4009,
    "isVariant": false,
    "isModExtend": false
  },
  {
    "name": "effectClassName4010",
    "id": 4010,
    "isVariant": false,
    "isModExtend": false
  },
  {
    "name": "effectClassName4011",
    "id": 4011,
    "isVariant": false,
    "isModExtend": false
  },
  {
    "name": "effectClassName4012",
    "id": 4012,
    "isVariant": false,
    "isModExtend": false
  },
  {
    "name": "effectClassName4013",
    "id": 4013,
    "isVariant": false,
    "isModExtend": false
  },
  {
    "name": "effectClassName4014",
    "id": 4014,
    "isVariant": false,
    "isModExtend": false
  },
  {
    "name": "effectClassName4015",
    "id": 4015,
    "isVariant": false,
    "isModExtend": false
  },
  {
    "name": "effectClassName101",
    "id": 101,
    "isVariant": false,
    "isModExtend": false
  },
  {
    "name": "effectClassName102",
    "id": 102,
    "isVariant": false,
    "isModExtend": false
  },
  {
    "name": "effectClassName7001",
    "id": 7001,
    "isVariant": false,
    "isModExtend": false
  },
  {
    "name": "effectClassName7002",
    "id": 7002,
    "isVariant": false,
    "isModExtend": false
  },
  {
    "name": "effectClassName30000",
    "id": 30000,
    "isVariant": false,
    "isModExtend": false
  }
]