[
  {
    "scale": 1,
    "layer": 101,
    "numMin": 3,
    "numMax": 3,
    "reputationNeed2": -1,
    "reputationNeed4": -1,
    "reputationNeed6": -1,
    "reputationNeed8": -1,
    "reputationNeed9": -1,
    "reputationNeed10": -1,
    "numAllMax": 999,
    "id": 1,
    "isVariant": false,
    "isModExtend": false
  },
  {
    "scale": 1,
    "layer": 102,
    "numMin": 1,
    "numMax": 1,
    "reputationNeed2": -1,
    "reputationNeed4": -1,
    "reputationNeed6": -1,
    "reputationNeed8": -1,
    "reputationNeed9": -1,
    "reputationNeed10": -1,
    "numAllMax": 999,
    "id": 2,
    "isVariant": false,
    "isModExtend": false
  },
  {
    "scale": 1,
    "layer": 6,
    "numMin": 2,
    "numMax": 3,
    "reputationNeed2": 150,
    "reputationNeed4": 250,
    "reputationNeed6": 500,
    "reputationNeed8": 825,
    "reputationNeed9": 1450,
    "reputationNeed10": 1450,
    "numAllMax": 9,
    "id": 3,
    "isVariant": false,
    "isModExtend": false
  },
  {
    "scale": 1,
    "layer": 5,
    "numMin": 2,
    "numMax": 3,
    "reputationNeed2": 150,
    "reputationNeed4": 250,
    "reputationNeed6": 500,
    "reputationNeed8": 825,
    "reputationNeed9": 1450,
    "reputationNeed10": 1450,
    "numAllMax": 9,
    "id": 4,
    "isVariant": false,
    "isModExtend": false
  },
  {
    "scale": 1,
    "layer": 4,
    "numMin": 3,
    "numMax": 3,
    "reputationNeed2": 150,
    "reputationNeed4": 250,
    "reputationNeed6": 500,
    "reputationNeed8": 825,
    "reputationNeed9": 1450,
    "reputationNeed10": 1450,
    "numAllMax": 9,
    "id": 5,
    "isVariant": false,
    "isModExtend": false
  },
  {
    "scale": 1,
    "layer": 3,
    "numMin": 2,
    "numMax": 3,
    "reputationNeed2": 150,
    "reputationNeed4": 250,
    "reputationNeed6": 500,
    "reputationNeed8": 825,
    "reputationNeed9": 1450,
    "reputationNeed10": 1450,
    "numAllMax": 9,
    "id": 6,
    "isVariant": false,
    "isModExtend": false
  },
  {
    "scale": 1,
    "layer": 2,
    "numMin": 2,
    "numMax": 3,
    "reputationNeed2": 150,
    "reputationNeed4": 250,
    "reputationNeed6": 500,
    "reputationNeed8": 825,
    "reputationNeed9": 1450,
    "reputationNeed10": 1450,
    "numAllMax": 9,
    "id": 7,
    "isVariant": false,
    "isModExtend": false
  },
  {
    "scale": 1,
    "layer": 1,
    "numMin": 3,
    "numMax": 3,
    "reputationNeed2": 150,
    "reputationNeed4": 250,
    "reputationNeed6": 500,
    "reputationNeed8": 825,
    "reputationNeed9": 1450,
    "reputationNeed10": 1450,
    "numAllMax": 9,
    "id": 8,
    "isVariant": false,
    "isModExtend": false
  },
  {
    "scale": 2,
    "layer": 101,
    "numMin": 6,
    "numMax": 6,
    "reputationNeed2": -1,
    "reputationNeed4": -1,
    "reputationNeed6": -1,
    "reputationNeed8": -1,
    "reputationNeed9": -1,
    "reputationNeed10": -1,
    "numAllMax": 999,
    "id": 9,
    "isVariant": false,
    "isModExtend": false
  },
  {
    "scale": 2,
    "layer": 102,
    "numMin": 2,
    "numMax": 2,
    "reputationNeed2": -1,
    "reputationNeed4": -1,
    "reputationNeed6": -1,
    "reputationNeed8": -1,
    "reputationNeed9": -1,
    "reputationNeed10": -1,
    "numAllMax": 999,
    "id": 10,
    "isVariant": false,
    "isModExtend": false
  },
  {
    "scale": 2,
    "layer": 6,
    "numMin": 3,
    "numMax": 5,
    "reputationNeed2": 150,
    "reputationNeed4": 250,
    "reputationNeed6": 500,
    "reputationNeed8": 825,
    "reputationNeed9": 1450,
    "reputationNeed10": 1450,
    "numAllMax": 15,
    "id": 11,
    "isVariant": false,
    "isModExtend": false
  },
  {
    "scale": 2,
    "layer": 5,
    "numMin": 3,
    "numMax": 5,
    "reputationNeed2": 150,
    "reputationNeed4": 250,
    "reputationNeed6": 500,
    "reputationNeed8": 825,
    "reputationNeed9": 1450,
    "reputationNeed10": 1450,
    "numAllMax": 15,
    "id": 12,
    "isVariant": false,
    "isModExtend": false
  },
  {
    "scale": 2,
    "layer": 4,
    "numMin": 3,
    "numMax": 5,
    "reputationNeed2": 150,
    "reputationNeed4": 250,
    "reputationNeed6": 500,
    "reputationNeed8": 825,
    "reputationNeed9": 1450,
    "reputationNeed10": 1450,
    "numAllMax": 15,
    "id": 13,
    "isVariant": false,
    "isModExtend": false
  },
  {
    "scale": 2,
    "layer": 3,
    "numMin": 3,
    "numMax": 5,
    "reputationNeed2": 150,
    "reputationNeed4": 250,
    "reputationNeed6": 500,
    "reputationNeed8": 825,
    "reputationNeed9": 1450,
    "reputationNeed10": 1450,
    "numAllMax": 15,
    "id": 14,
    "isVariant": false,
    "isModExtend": false
  },
  {
    "scale": 2,
    "layer": 2,
    "numMin": 3,
    "numMax": 5,
    "reputationNeed2": 150,
    "reputationNeed4": 250,
    "reputationNeed6": 500,
    "reputationNeed8": 825,
    "reputationNeed9": 1450,
    "reputationNeed10": 1450,
    "numAllMax": 15,
    "id": 15,
    "isVariant": false,
    "isModExtend": false
  },
  {
    "scale": 2,
    "layer": 1,
    "numMin": 3,
    "numMax": 5,
    "reputationNeed2": 150,
    "reputationNeed4": 250,
    "reputationNeed6": 500,
    "reputationNeed8": 825,
    "reputationNeed9": 1450,
    "reputationNeed10": 1450,
    "numAllMax": 15,
    "id": 16,
    "isVariant": false,
    "isModExtend": false
  },
  {
    "scale": 3,
    "layer": 101,
    "numMin": 12,
    "numMax": 12,
    "reputationNeed2": -1,
    "reputationNeed4": -1,
    "reputationNeed6": -1,
    "reputationNeed8": -1,
    "reputationNeed9": -1,
    "reputationNeed10": -1,
    "numAllMax": 999,
    "id": 17,
    "isVariant": false,
    "isModExtend": false
  },
  {
    "scale": 3,
    "layer": 102,
    "numMin": 4,
    "numMax": 4,
    "reputationNeed2": -1,
    "reputationNeed4": -1,
    "reputationNeed6": -1,
    "reputationNeed8": -1,
    "reputationNeed9": -1,
    "reputationNeed10": -1,
    "numAllMax": 999,
    "id": 18,
    "isVariant": false,
    "isModExtend": false
  },
  {
    "scale": 3,
    "layer": 6,
    "numMin": 4,
    "numMax": 7,
    "reputationNeed2": 150,
    "reputationNeed4": 250,
    "reputationNeed6": 500,
    "reputationNeed8": 825,
    "reputationNeed9": 1450,
    "reputationNeed10": 1450,
    "numAllMax": 21,
    "id": 19,
    "isVariant": false,
    "isModExtend": false
  },
  {
    "scale": 3,
    "layer": 5,
    "numMin": 4,
    "numMax": 7,
    "reputationNeed2": 150,
    "reputationNeed4": 250,
    "reputationNeed6": 500,
    "reputationNeed8": 825,
    "reputationNeed9": 1450,
    "reputationNeed10": 1450,
    "numAllMax": 21,
    "id": 20,
    "isVariant": false,
    "isModExtend": false
  },
  {
    "scale": 3,
    "layer": 4,
    "numMin": 5,
    "numMax": 7,
    "reputationNeed2": 150,
    "reputationNeed4": 250,
    "reputationNeed6": 500,
    "reputationNeed8": 825,
    "reputationNeed9": 1450,
    "reputationNeed10": 1450,
    "numAllMax": 21,
    "id": 21,
    "isVariant": false,
    "isModExtend": false
  },
  {
    "scale": 3,
    "layer": 3,
    "numMin": 4,
    "numMax": 7,
    "reputationNeed2": 150,
    "reputationNeed4": 250,
    "reputationNeed6": 500,
    "reputationNeed8": 825,
    "reputationNeed9": 1450,
    "reputationNeed10": 1450,
    "numAllMax": 21,
    "id": 22,
    "isVariant": false,
    "isModExtend": false
  },
  {
    "scale": 3,
    "layer": 2,
    "numMin": 4,
    "numMax": 7,
    "reputationNeed2": 150,
    "reputationNeed4": 250,
    "reputationNeed6": 500,
    "reputationNeed8": 825,
    "reputationNeed9": 1450,
    "reputationNeed10": 1450,
    "numAllMax": 21,
    "id": 23,
    "isVariant": false,
    "isModExtend": false
  },
  {
    "scale": 3,
    "layer": 1,
    "numMin": 4,
    "numMax": 7,
    "reputationNeed2": 150,
    "reputationNeed4": 250,
    "reputationNeed6": 500,
    "reputationNeed8": 825,
    "reputationNeed9": 1450,
    "reputationNeed10": 1450,
    "numAllMax": 21,
    "id": 24,
    "isVariant": false,
    "isModExtend": false
  },
  {
    "scale": 4,
    "layer": 101,
    "numMin": 18,
    "numMax": 18,
    "reputationNeed2": -1,
    "reputationNeed4": -1,
    "reputationNeed6": -1,
    "reputationNeed8": -1,
    "reputationNeed9": -1,
    "reputationNeed10": -1,
    "numAllMax": 999,
    "id": 25,
    "isVariant": false,
    "isModExtend": false
  },
  {
    "scale": 4,
    "layer": 102,
    "numMin": 6,
    "numMax": 6,
    "reputationNeed2": -1,
    "reputationNeed4": -1,
    "reputationNeed6": -1,
    "reputationNeed8": -1,
    "reputationNeed9": -1,
    "reputationNeed10": -1,
    "numAllMax": 999,
    "id": 26,
    "isVariant": false,
    "isModExtend": false
  },
  {
    "scale": 4,
    "layer": 6,
    "numMin": 5,
    "numMax": 9,
    "reputationNeed2": 150,
    "reputationNeed4": 250,
    "reputationNeed6": 500,
    "reputationNeed8": 825,
    "reputationNeed9": 1450,
    "reputationNeed10": 1450,
    "numAllMax": 27,
    "id": 27,
    "isVariant": false,
    "isModExtend": false
  },
  {
    "scale": 4,
    "layer": 5,
    "numMin": 5,
    "numMax": 9,
    "reputationNeed2": 150,
    "reputationNeed4": 250,
    "reputationNeed6": 500,
    "reputationNeed8": 825,
    "reputationNeed9": 1450,
    "reputationNeed10": 1450,
    "numAllMax": 27,
    "id": 28,
    "isVariant": false,
    "isModExtend": false
  },
  {
    "scale": 4,
    "layer": 4,
    "numMin": 6,
    "numMax": 9,
    "reputationNeed2": 150,
    "reputationNeed4": 250,
    "reputationNeed6": 500,
    "reputationNeed8": 825,
    "reputationNeed9": 1450,
    "reputationNeed10": 1450,
    "numAllMax": 27,
    "id": 29,
    "isVariant": false,
    "isModExtend": false
  },
  {
    "scale": 4,
    "layer": 3,
    "numMin": 5,
    "numMax": 9,
    "reputationNeed2": 150,
    "reputationNeed4": 250,
    "reputationNeed6": 500,
    "reputationNeed8": 825,
    "reputationNeed9": 1450,
    "reputationNeed10": 1450,
    "numAllMax": 27,
    "id": 30,
    "isVariant": false,
    "isModExtend": false
  },
  {
    "scale": 4,
    "layer": 2,
    "numMin": 5,
    "numMax": 9,
    "reputationNeed2": 150,
    "reputationNeed4": 250,
    "reputationNeed6": 500,
    "reputationNeed8": 825,
    "reputationNeed9": 1450,
    "reputationNeed10": 1450,
    "numAllMax": 27,
    "id": 31,
    "isVariant": false,
    "isModExtend": false
  },
  {
    "scale": 4,
    "layer": 1,
    "numMin": 5,
    "numMax": 9,
    "reputationNeed2": 150,
    "reputationNeed4": 250,
    "reputationNeed6": 500,
    "reputationNeed8": 825,
    "reputationNeed9": 1450,
    "reputationNeed10": 1450,
    "numAllMax": 27,
    "id": 32,
    "isVariant": false,
    "isModExtend": false
  },
  {
    "scale": 5,
    "layer": 101,
    "numMin": 18,
    "numMax": 18,
    "reputationNeed2": -1,
    "reputationNeed4": -1,
    "reputationNeed6": -1,
    "reputationNeed8": -1,
    "reputationNeed9": -1,
    "reputationNeed10": -1,
    "numAllMax": 999,
    "id": 33,
    "isVariant": false,
    "isModExtend": false
  },
  {
    "scale": 5,
    "layer": 102,
    "numMin": 6,
    "numMax": 6,
    "reputationNeed2": -1,
    "reputationNeed4": -1,
    "reputationNeed6": -1,
    "reputationNeed8": -1,
    "reputationNeed9": -1,
    "reputationNeed10": -1,
    "numAllMax": 999,
    "id": 34,
    "isVariant": false,
    "isModExtend": false
  },
  {
    "scale": 5,
    "layer": 6,
    "numMin": 5,
    "numMax": 9,
    "reputationNeed2": 150,
    "reputationNeed4": 250,
    "reputationNeed6": 500,
    "reputationNeed8": 825,
    "reputationNeed9": 1450,
    "reputationNeed10": 1450,
    "numAllMax": 27,
    "id": 35,
    "isVariant": false,
    "isModExtend": false
  },
  {
    "scale": 5,
    "layer": 5,
    "numMin": 5,
    "numMax": 9,
    "reputationNeed2": 150,
    "reputationNeed4": 250,
    "reputationNeed6": 500,
    "reputationNeed8": 825,
    "reputationNeed9": 1450,
    "reputationNeed10": 1450,
    "numAllMax": 27,
    "id": 36,
    "isVariant": false,
    "isModExtend": false
  },
  {
    "scale": 5,
    "layer": 4,
    "numMin": 6,
    "numMax": 9,
    "reputationNeed2": 150,
    "reputationNeed4": 250,
    "reputationNeed6": 500,
    "reputationNeed8": 825,
    "reputationNeed9": 1450,
    "reputationNeed10": 1450,
    "numAllMax": 27,
    "id": 37,
    "isVariant": false,
    "isModExtend": false
  },
  {
    "scale": 5,
    "layer": 3,
    "numMin": 5,
    "numMax": 9,
    "reputationNeed2": 150,
    "reputationNeed4": 250,
    "reputationNeed6": 500,
    "reputationNeed8": 825,
    "reputationNeed9": 1450,
    "reputationNeed10": 1450,
    "numAllMax": 27,
    "id": 38,
    "isVariant": false,
    "isModExtend": false
  },
  {
    "scale": 5,
    "layer": 2,
    "numMin": 5,
    "numMax": 9,
    "reputationNeed2": 150,
    "reputationNeed4": 250,
    "reputationNeed6": 500,
    "reputationNeed8": 825,
    "reputationNeed9": 1450,
    "reputationNeed10": 1450,
    "numAllMax": 27,
    "id": 39,
    "isVariant": false,
    "isModExtend": false
  },
  {
    "scale": 5,
    "layer": 1,
    "numMin": 5,
    "numMax": 9,
    "reputationNeed2": 150,
    "reputationNeed4": 250,
    "reputationNeed6": 500,
    "reputationNeed8": 825,
    "reputationNeed9": 1450,
    "reputationNeed10": 1450,
    "numAllMax": 27,
    "id": 40,
    "isVariant": false,
    "isModExtend": false
  }
]