[
  {
    "key": "dragonHide",
    "value": 9901134,
    "id": 1,
    "isVariant": false,
    "isModExtend": false
  },
  {
    "key": "intimacyMax",
    "value": 500,
    "id": 2,
    "isVariant": false,
    "isModExtend": false
  },
  {
    "key": "oneIntimacyMax",
    "value": 100,
    "id": 3,
    "isVariant": false,
    "isModExtend": false
  },
  {
    "key": "talkUpInti",
    "value": 5,
    "id": 4,
    "isVariant": false,
    "isModExtend": false
  },
  {
    "key": "downInti",
    "value": 10,
    "id": 5,
    "isVariant": false,
    "isModExtend": false
  },
  {
    "key": "dragonLuck1",
    "value": 700007,
    "id": 6,
    "isVariant": false,
    "isModExtend": false
  },
  {
    "key": "dragonLuck2",
    "value": 700008,
    "id": 7,
    "isVariant": false,
    "isModExtend": false
  },
  {
    "key": "dragonLuck3",
    "value": 700009,
    "id": 8,
    "isVariant": false,
    "isModExtend": false
  },
  {
    "key": "dragonLuck4",
    "value": 700126,
    "id": 9,
    "isVariant": false,
    "isModExtend": false
  },
  {
    "key": "dragonLuck5",
    "value": 700188,
    "id": 10,
    "isVariant": false,
    "isModExtend": false
  },
  {
    "key": "dragonLuck6_1",
    "value": 700189,
    "id": 11,
    "isVariant": false,
    "isModExtend": false
  },
  {
    "key": "dragonLuck6_2",
    "value": 700190,
    "id": 12,
    "isVariant": false,
    "isModExtend": false
  },
  {
    "key": "dragonUnit1",
    "value": 700007,
    "id": 13,
    "isVariant": false,
    "isModExtend": false
  },
  {
    "key": "dragonUnit2",
    "value": 700008,
    "id": 14,
    "isVariant": false,
    "isModExtend": false
  },
  {
    "key": "dragonUnit3",
    "value": 700009,
    "id": 15,
    "isVariant": false,
    "isModExtend": false
  },
  {
    "key": "dragonUnit4",
    "value": 1931,
    "id": 16,
    "isVariant": false,
    "isModExtend": false
  },
  {
    "key": "dragonUnit5",
    "value": 1931,
    "id": 17,
    "isVariant": false,
    "isModExtend": false
  },
  {
    "key": "dragonUnit6_1",
    "value": 3100001,
    "id": 18,
    "isVariant": false,
    "isModExtend": false
  },
  {
    "key": "dragonUnit6_2",
    "value": 3100002,
    "id": 19,
    "isVariant": false,
    "isModExtend": false
  },
  {
    "key": "dragonHalo6_1",
    "value": 700189,
    "id": 20,
    "isVariant": false,
    "isModExtend": false
  },
  {
    "key": "dragonHalo6_2",
    "value": 700190,
    "id": 21,
    "isVariant": false,
    "isModExtend": false
  },
  {
    "key": "dragonFate",
    "value": 2803,
    "id": 22,
    "isVariant": false,
    "isModExtend": false
  },
  {
    "key": "changeShapeCool",
    "value": 500,
    "id": 23,
    "isVariant": false,
    "isModExtend": false
  },
  {
    "key": "transDramaBoy",
    "value": 1304650,
    "id": 24,
    "isVariant": false,
    "isModExtend": false
  },
  {
    "key": "transDramaGril",
    "value": 1304650,
    "id": 25,
    "isVariant": false,
    "isModExtend": false
  }
]