[
  {
    "initWeight": 100,
    "addWeight": 50,
    "reduceWeight": 0,
    "areaValue2": 1000.0,
    "areaValue4": 1000.0,
    "areaValue6": 1000.0,
    "areaValue8": 1000.0,
    "areaValue10": 1000.0,
    "id": 1,
    "isVariant": false,
    "isModExtend": false
  },
  {
    "initWeight": 100,
    "addWeight": 0,
    "reduceWeight": -100,
    "areaValue2": 14.56,
    "areaValue4": 9.58,
    "areaValue6": 6.09,
    "areaValue8": 3.86,
    "areaValue10": 2.32,
    "id": 3,
    "isVariant": false,
    "isModExtend": false
  },
  {
    "initWeight": 100,
    "addWeight": 0,
    "reduceWeight": -100,
    "areaValue2": 4.48,
    "areaValue4": 4.62,
    "areaValue6": 6.08,
    "areaValue8": 7.9,
    "areaValue10": 10.41,
    "id": 4,
    "isVariant": false,
    "isModExtend": false
  },
  {
    "initWeight": 100,
    "addWeight": 200,
    "reduceWeight": 0,
    "areaValue2": 250.0,
    "areaValue4": 391.0,
    "areaValue6": 622.0,
    "areaValue8": 987.0,
    "areaValue10": 1651.0,
    "id": 7,
    "isVariant": false,
    "isModExtend": false
  },
  {
    "initWeight": 50,
    "addWeight": 0,
    "reduceWeight": 0,
    "areaValue2": 0.0,
    "areaValue4": 0.0,
    "areaValue6": 0.0,
    "areaValue8": 0.0,
    "areaValue10": 0.0,
    "id": 8,
    "isVariant": false,
    "isModExtend": false
  },
  {
    "initWeight": 50,
    "addWeight": 0,
    "reduceWeight": 0,
    "areaValue2": 0.0,
    "areaValue4": 0.0,
    "areaValue6": 0.0,
    "areaValue8": 0.0,
    "areaValue10": 0.0,
    "id": 9,
    "isVariant": false,
    "isModExtend": false
  }
]