[
  {
    "npcId": 6103,
    "skillBaseID": 24113,
    "phycicalDmg": "&24113_xjwl",
    "weaponType": -99,
    "magicDmg": "-99",
    "magicType": -99,
    "missileID": 241131,
    "shotCD": "-99",
    "skillEffect": "-99",
    "offsetPosi": "-99",
    "skillSub": "241131",
    "id": 1,
    "isVariant": false,
    "isModExtend": false
  },
  {
    "npcId": 6103,
    "skillBaseID": 24111,
    "phycicalDmg": "&24111_qhwl",
    "weaponType": -99,
    "magicDmg": "-99",
    "magicType": -99,
    "missileID": 241111,
    "shotCD": "-99",
    "skillEffect": "-99",
    "offsetPosi": "-99",
    "skillSub": "-99",
    "id": 2,
    "isVariant": false,
    "isModExtend": false
  },
  {
    "npcId": 6089,
    "skillBaseID": 56111,
    "phycicalDmg": "-99",
    "weaponType": -99,
    "magicDmg": "-99",
    "magicType": -99,
    "missileID": 561112,
    "shotCD": "-99",
    "skillEffect": "3561111|3561114",
    "offsetPosi": "-99",
    "skillSub": "561112|561113",
    "id": 3,
    "isVariant": false,
    "isModExtend": false
  },
  {
    "npcId": 6097,
    "skillBaseID": 51111,
    "phycicalDmg": "-99",
    "weaponType": -99,
    "magicDmg": "&51111_hfwl",
    "magicType": -99,
    "missileID": 511111,
    "shotCD": "-99",
    "skillEffect": "-99",
    "offsetPosi": "-99",
    "skillSub": "511111",
    "id": 4,
    "isVariant": false,
    "isModExtend": false
  },
  {
    "npcId": 6090,
    "skillBaseID": 55115,
    "phycicalDmg": "-99",
    "weaponType": -99,
    "magicDmg": "&55115_sbwl",
    "magicType": -99,
    "missileID": -99,
    "shotCD": "-99",
    "skillEffect": "-99",
    "offsetPosi": "-99",
    "skillSub": "551154|551155",
    "id": 5,
    "isVariant": false,
    "isModExtend": false
  },
  {
    "npcId": 6088,
    "skillBaseID": 22113,
    "phycicalDmg": "&22113_zjwl",
    "weaponType": -99,
    "magicDmg": "-99",
    "magicType": -99,
    "missileID": 221131,
    "shotCD": "-99",
    "skillEffect": "-99",
    "offsetPosi": "-99",
    "skillSub": "221132",
    "id": 6,
    "isVariant": false,
    "isModExtend": false
  }
]